gorgou/__init__.py
gorgou/cache.py
gorgou/download.py
gorgou/iciba.py
gorgou/request.py
gorgou/sql/__init__.py
gorgou/sql/mongo.py
gorgou/sql/mssql.py
gorgou/sql/mysql.py
gorgou/sql/sqlite3.py
gorgou/x/__init__.py
gorgou/x/emailx.py
gorgou/x/ftpx.py
gorgou/x/jsonx.py
gorgou/x/sysx.py
gorgou-1.1.3.dist-info/DESCRIPTION.rst
gorgou-1.1.3.dist-info/METADATA
gorgou-1.1.3.dist-info/RECORD
gorgou-1.1.3.dist-info/WHEEL
gorgou-1.1.3.dist-info/metadata.json
gorgou-1.1.3.dist-info/top_level.txt
