Metadata-Version: 2.0
Name: gorgou
Version: 1.1.3
Summary: The most valuable and useful functions we encounter with everyday!However,it is in beta version currently.
Home-page: UNKNOWN
Author: Ray Wang
Author-email: sedativearchi@hotmail.com
License: MIT License
Keywords: gorgou,library
Platform: any
